JiqiZhixin2019GaofenJiaochengYuyan/README.md
JiqiZhixin2019GaofenJiaochengYuyan/__init__.py
JiqiZhixin2019GaofenJiaochengYuyan/__main__.py
JiqiZhixin2019GaofenJiaochengYuyan/file.epub
JiqiZhixin2019GaofenJiaochengYuyan/index.html
JiqiZhixin2019GaofenJiaochengYuyan/css/__init__.py
JiqiZhixin2019GaofenJiaochengYuyan/css/annotations.css
JiqiZhixin2019GaofenJiaochengYuyan/css/main.css
JiqiZhixin2019GaofenJiaochengYuyan/css/normalize.css
JiqiZhixin2019GaofenJiaochengYuyan/css/popup.css
JiqiZhixin2019GaofenJiaochengYuyan/font/__init__.py
JiqiZhixin2019GaofenJiaochengYuyan/font/fontello.eot
JiqiZhixin2019GaofenJiaochengYuyan/font/fontello.svg
JiqiZhixin2019GaofenJiaochengYuyan/font/fontello.ttf
JiqiZhixin2019GaofenJiaochengYuyan/font/fontello.woff
JiqiZhixin2019GaofenJiaochengYuyan/img/__init__.py
JiqiZhixin2019GaofenJiaochengYuyan/img/annotator-glyph-sprite.png
JiqiZhixin2019GaofenJiaochengYuyan/img/annotator-icon-sprite.png
JiqiZhixin2019GaofenJiaochengYuyan/img/apple-touch-icon.png
JiqiZhixin2019GaofenJiaochengYuyan/img/cancelfullscreen.png
JiqiZhixin2019GaofenJiaochengYuyan/img/close.png
JiqiZhixin2019GaofenJiaochengYuyan/img/fullscreen.png
JiqiZhixin2019GaofenJiaochengYuyan/img/loader.gif
JiqiZhixin2019GaofenJiaochengYuyan/img/menu-icon.png
JiqiZhixin2019GaofenJiaochengYuyan/img/save.png
JiqiZhixin2019GaofenJiaochengYuyan/img/saved.png
JiqiZhixin2019GaofenJiaochengYuyan/img/settings-s.png
JiqiZhixin2019GaofenJiaochengYuyan/img/settings.png
JiqiZhixin2019GaofenJiaochengYuyan/img/star.png
JiqiZhixin2019GaofenJiaochengYuyan/js/__init__.py
JiqiZhixin2019GaofenJiaochengYuyan/js/epub.js
JiqiZhixin2019GaofenJiaochengYuyan/js/epub.min.js
JiqiZhixin2019GaofenJiaochengYuyan/js/epub.min.map
JiqiZhixin2019GaofenJiaochengYuyan/js/hooks.min.js
JiqiZhixin2019GaofenJiaochengYuyan/js/hooks.min.map
JiqiZhixin2019GaofenJiaochengYuyan/js/reader.js
JiqiZhixin2019GaofenJiaochengYuyan/js/reader.js.map
JiqiZhixin2019GaofenJiaochengYuyan/js/reader.min.js
jiqi_zhixin_2019_gaofen_jiaocheng_yuyan-2024.3.5.0.dist-info/METADATA
jiqi_zhixin_2019_gaofen_jiaocheng_yuyan-2024.3.5.0.dist-info/WHEEL
jiqi_zhixin_2019_gaofen_jiaocheng_yuyan-2024.3.5.0.dist-info/entry_points.txt
jiqi_zhixin_2019_gaofen_jiaocheng_yuyan-2024.3.5.0.dist-info/top_level.txt
jiqi_zhixin_2019_gaofen_jiaocheng_yuyan-2024.3.5.0.dist-info/RECORD
